LICENSE
MANIFEST.in
README.rst
setup.py
tox.ini
youneedme/__init__.py
youneedme/exceptions.py
youneedme.egg-info/PKG-INFO
youneedme.egg-info/SOURCES.txt
youneedme.egg-info/dependency_links.txt
youneedme.egg-info/entry_points.txt
youneedme.egg-info/requires.txt
youneedme.egg-info/top_level.txt