Metadata-Version: 1.1
Name: youneedme
Version: 0.0.1
Summary: You need me, but I need you too.
Home-page: https://bitbucket.org/johannestaas/youneedme
Author: Johan Nestaas
Author-email: johannestaas@gmail.com
License: GPLv3
Keywords: circular
Platform: UNKNOWN
Classifier: Development Status :: 3 - Alpha
Classifier: Environment :: Console
Classifier: Environment :: X11 Applications :: Qt
Classifier: Environment :: MacOS X
Classifier: Environment :: Win32 (MS Windows)
Classifier: Operating System :: POSIX
Classifier: Operating System :: MacOS :: MacOS X
Classifier: Operating System :: Microsoft :: Windows
Classifier: Programming Language :: Python
